helga_trade/__init__.py
helga_trade/helga_trade.py
helga_trade-1.0.1.dist-info/DESCRIPTION.rst
helga_trade-1.0.1.dist-info/METADATA
helga_trade-1.0.1.dist-info/RECORD
helga_trade-1.0.1.dist-info/WHEEL
helga_trade-1.0.1.dist-info/entry_points.txt
helga_trade-1.0.1.dist-info/metadata.json
helga_trade-1.0.1.dist-info/top_level.txt
helga_trade-1.0.1.dist-info/zip-safe
tests/__init__.py
tests/test_trade.py
