Metadata-Version: 2.0
Name: helga-trade
Version: 1.0.1
Summary: Stock, crypto, forex trade information plugin for helga
Home-page: UNKNOWN
Author: Jon Robison
Author-email: narfman0@gmail.com
License: LICENSE
Keywords: irc bot trade
Platform: UNKNOWN
Classifier: Development Status :: 4 - Beta
Classifier: Topic :: Communications :: Chat :: Internet Relay Chat
Classifier: License :: OSI Approved :: GNU General Public License v3 (GPLv3)
Classifier: Operating System :: OS Independent
Classifier: Programming Language :: Python
Classifier: Topic :: Software Development :: Libraries :: Python Modules
Classifier: Topic :: Communications :: Chat :: Internet Relay Chat
Requires-Dist: googlefinance
Requires-Dist: helga
Requires-Dist: requests
